[{"zh": "莫斯科", "en": "Moscow"}, {"zh": "圣彼得堡", "en": "St Petersburg"}, {"zh": "伊尔库茨克", "en": "Irkutsk"}, {"zh": "符拉迪沃斯托克(海参崴)", "en": "Vladivostok"}, {"zh": "弗拉基米尔", "en": "Vladimir"}, {"zh": "苏兹达尔", "en": "Suzdal"}, {"zh": "贝加尔湖", "en": "Lake baikal"}, {"zh": "叶卡捷琳堡", "en": "Yekaterinburg"}, {"zh": "谢尔盖耶夫", "en": "Sergiyev Posad"}, {"zh": "利斯特维扬卡", "en": "Listvyanka"}, {"zh": "摩尔曼斯克", "en": "Murmansk"}, {"zh": "奥尔洪岛", "en": "Olkhon"}, {"zh": "新西伯利亚", "en": "Novosibirsk"}, {"zh": "喀山", "en": "Kazan"}, {"zh": "诺夫哥罗德", "en": "Novgorod"}, {"zh": "索契", "en": "Sochi"}, {"zh": "布拉戈维申斯克(海兰泡)", "en": "Blagoveshchensk"}, {"zh": "哈巴罗夫斯克(伯力)", "en": "Khabarovsk"}, {"zh": "下诺夫哥罗德", "en": "Nizhny Novgorod"}, {"zh": "俄罗斯维堡", "en": "Vyborg"}, {"zh": "雅罗斯拉夫尔", "en": "Yaroslavl"}, {"zh": "乌兰乌德", "en": "Ulan-Ude"}, {"zh": "赤塔", "en": "Chita"}, {"zh": "雅尔塔", "en": "Yalta"}, {"zh": "克里米亚", "en": "Crimea"}, {"zh": "基日", "en": "Kizhi"}, {"zh": "伏尔加格勒", "en": "Volgograd"}, {"zh": "加里宁格勒", "en": "Kaliningrad"}, {"zh": "图拉", "en": "Tula"}, {"zh": "后贝加尔斯克", "en": "Zabaykalsk"}]