[{"zh": "开普敦", "en": "Cape Town"}, {"zh": "约翰内斯堡", "en": "Johannesburg"}, {"zh": "比勒陀利亚", "en": "Pretoria"}, {"zh": "太阳城", "en": "Sun City"}, {"zh": "伊丽莎白港", "en": "Port Elizabeth"}, {"zh": "克鲁格国家公园", "en": "Kruger National Park"}, {"zh": "德班", "en": "Durban"}, {"zh": "西蒙镇", "en": "Simon's Town"}, {"zh": "乔治(西开普省)", "en": "George, Western Cape"}, {"zh": "克尼斯纳", "en": "Knysna"}, {"zh": "布隆方丹", "en": "Bloemfontein"}, {"zh": "奥茨胡恩", "en": "Oudtshoorn"}, {"zh": "金伯利", "en": "Kimberley"}, {"zh": "斯韦伦丹", "en": "Swellendam"}, {"zh": "索韦托", "en": "Soweto"}, {"zh": "杭斯拜", "en": "Gansbaai"}, {"zh": "东伦敦", "en": "East London"}, {"zh": "姆普马兰加", "en": "Mpumalanga"}, {"zh": "彼得马里茨堡", "en": "Pietermaritzburg"}, {"zh": "自由邦省", "en": "Free state"}, {"zh": "肯普顿帕克", "en": "Kempton Park"}, {"zh": "波罗克瓦尼", "en": "Polokwane"}, {"zh": "斯特兰芬泰因", "en": "Strandfontein"}, {"zh": "Springbok", "en": "Springbok"}]