[{"zh": "卢塞恩", "en": "Lucerne"}, {"zh": "苏黎世", "en": "Zurich"}, {"zh": "因特拉肯", "en": "Interlaken"}, {"zh": "日内瓦", "en": "Geneva"}, {"zh": "伯尔尼", "en": "Bern"}, {"zh": "洛桑", "en": "Lausanne"}, {"zh": "蒙特勒", "en": "Montreux"}, {"zh": "采尔马特", "en": "Zermatt"}, {"zh": "巴塞尔", "en": "Basel"}, {"zh": "施皮茨", "en": "Spiez"}, {"zh": "劳特布龙嫩", "en": "Lauterbrunnen"}, {"zh": "格林德瓦", "en": "Grindelwald"}, {"zh": "米伦", "en": "Murren"}, {"zh": "图恩", "en": "Thun"}, {"zh": "卢加诺", "en": "Lugano"}, {"zh": "沃韦", "en": "Vevey"}, {"zh": "文根", "en": "Wengen"}, {"zh": "沙夫豪森", "en": "Schaffhausen"}, {"zh": "布里恩茨", "en": "Brienz"}, {"zh": "韦吉斯", "en": "Weggis"}, {"zh": "英格堡", "en": "Engelberg"}, {"zh": "施泰因", "en": "Stein am Rhein"}, {"zh": "龙疆", "en": "Lungern"}, {"zh": "圣加仑", "en": "St Gallen"}, {"zh": "圣莫里茨", "en": "Sankt Moritz"}, {"zh": "库尔", "en": "Chur"}, {"zh": "尼永", "en": "Nyon"}, {"zh": "莫尔日", "en": "Morges"}, {"zh": "锡永", "en": "Sion"}, {"zh": "洛迦诺", "en": "Locarno"}, {"zh": "布里格", "en": "Brig"}, {"zh": "洛伊克巴德", "en": "Leukerbad"}, {"zh": "巴登", "en": "Baden"}, {"zh": "菲茨瑙", "en": "Vitznau"}, {"zh": "贝林佐纳", "en": "Bellinzona"}, {"zh": "达沃斯", "en": "Davos"}, {"zh": "弗里堡", "en": "Fribourg"}, {"zh": "纳沙泰尔", "en": "Neuchatel"}, {"zh": "楚格", "en": "Zug"}, {"zh": "莱茵瀑布边的诺伊豪森", "en": "Neuhausen am Rheinfall"}, {"zh": "伊瑟尔特瓦尔德", "en": "Iseltwald"}, {"zh": "安德马特", "en": "Andermatt"}, {"zh": "格吕耶尔", "en": "Gruyeres"}, {"zh": "比尔", "en": "Biel"}, {"zh": "谢布尔", "en": "Chexbres"}, {"zh": "爱蒙塔尔", "en": "Emmental"}, {"zh": "茨魏西门", "en": "Zweisimmen"}, {"zh": "马蒂尼", "en": "Martigny"}, {"zh": "费尔施", "en": "Fiesch"}, {"zh": "迈林根", "en": "Meiringen"}, {"zh": "温特图尔", "en": "Winterthur"}, {"zh": "基亚索", "en": "Chiasso"}, {"zh": "瑞士罗滕堡", "en": "Rothenburg"}, {"zh": "吉梅尔瓦尔德", "en": "Gimmelwald"}, {"zh": "塔什", "en": "Täsch"}, {"zh": "伊韦尔东", "en": "Yverdon-Les-Bains"}, {"zh": "萨甘斯", "en": "Sargans"}, {"zh": "坎德施泰格", "en": "Kandersteg"}, {"zh": "阿彭策尔", "en": "Appenzell"}, {"zh": "施库尔", "en": "Schuls"}]