[{"zh": "伊斯兰堡", "en": "Islamabad "}, {"zh": "拉合尔", "en": "Lahore"}, {"zh": "卡拉奇", "en": "Karachi"}, {"zh": "白沙瓦", "en": "Peshawar"}, {"zh": "吉尔吉特", "en": "Gilgit"}, {"zh": "罕萨", "en": "Hunza"}, {"zh": "苏斯特", "en": "Sost"}, {"zh": "塔克西拉", "en": "Taxila"}, {"zh": "斯卡都", "en": "Skardu"}, {"zh": "帕苏", "en": "Passu"}, {"zh": "木尔坦", "en": "Multan"}, {"zh": "奎达", "en": "Quetta"}, {"zh": "穆里", "en": "Murree"}, {"zh": "斯瓦特山谷", "en": "Swat Valley"}, {"zh": "吉德拉尔", "en": "Chitral"}, {"zh": "纳兰", "en": "Naran"}, {"zh": "摩亨佐达罗", "en": "Moenjodaro"}, {"zh": "瓜达尔", "en": "Gwadar"}, {"zh": "哈拉帕", "en": "Harappa"}, {"zh": "南迦帕尔巴特峰", "en": "Nanga Parbat"}, {"zh": "芒罗堡", "en": "Fort Munro"}]